README.md
setup.py
bin/pst
pst/_version.py
pst.egg-info/PKG-INFO
pst.egg-info/SOURCES.txt
pst.egg-info/dependency_links.txt
pst.egg-info/requires.txt
pst.egg-info/top_level.txt