Metadata-Version: 2.1
Name: pst
Version: 1.5.3
Summary: A reproduction of pstree
Home-page: https://github.com/mixedconnections/pst
Author: mixed.connections
Author-email: mixed.connections2@gmail.com
License: MIT
Keywords: shell pstree
Platform: UNKNOWN
Classifier: Programming Language :: Python :: 3
Classifier: License :: OSI Approved :: MIT License
Classifier: Operating System :: POSIX
Classifier: Topic :: Utilities
